sent2vec/__init__.py
sent2vec/constants.py
sent2vec/splitter.py
sent2vec/vectorizer.py
sent2vec-0.3.0.dist-info/LICENSE
sent2vec-0.3.0.dist-info/METADATA
sent2vec-0.3.0.dist-info/WHEEL
sent2vec-0.3.0.dist-info/entry_points.txt
sent2vec-0.3.0.dist-info/top_level.txt
sent2vec-0.3.0.dist-info/RECORD
