Metadata-Version: 2.1
Name: sent2vec
Version: 0.3.0
Summary: How to encode sentences in a high-dimensional vector space, a.k.a., sentence embedding.
Home-page: https://github.com/pdrm83/sent2vec
Author: Pedram Ataee
Author-email: pedram.ataee@gmail.com
License: MIT
Platform: UNKNOWN
Classifier: License :: OSI Approved :: MIT License
Classifier: Programming Language :: Python :: 3
Classifier: Programming Language :: Python :: 3.7
License-File: LICENSE
Requires-Dist: transformers
Requires-Dist: torch
Requires-Dist: numpy
Requires-Dist: gensim
Requires-Dist: spacy
Requires-Dist: pytest
